MANIFEST.in
setup.py
src/python_webid.egg-info/PKG-INFO
src/python_webid.egg-info/SOURCES.txt
src/python_webid.egg-info/dependency_links.txt
src/python_webid.egg-info/not-zip-safe
src/python_webid.egg-info/requires.txt
src/python_webid.egg-info/top_level.txt
src/webid/__init__.py
src/webid/cert.py
src/webid/client.py
src/webid/constants.py
src/webid/earl.py
src/webid/fetcher.py
src/webid/serializers.py
src/webid/validator.py
src/webid/webidchecks.py
src/webid/xcollections.py
src/webid/data/RelyingParty.n3
src/webid/data/RelyingPartyExample.n3
src/webid/data/sample.cfg