Metadata-Version: 1.1
Name: python-webid
Version: 0.2
Summary: A python lib implementing server-side validation     and client ssl authentication following the WebID spec
Home-page: UNKNOWN
Author: Ben Carrillo
Author-email: bennomadic at gmail dot com
License: UNKNOWN
Download-URL: https://github.com/bennomadic/python-webid.git
Keywords: WebID,foaf,ssl,x509,certificate,client certificate,authentication
Platform: any
Classifier: Development Status :: 3 - Alpha
Classifier: Intended Audience :: Developers
Classifier: License :: OSI Approved :: GNU General Public License (GPL)
Classifier: Operating System :: OS Independent
Classifier: Programming Language :: Python
Classifier: Topic :: Internet :: WWW/HTTP
Classifier: Topic :: Software Development :: Libraries :: Python Modules
